ghapi_conversion/__init__.py
ghapi_conversion/__main__.py
ghapi_conversion/utils.py
ghapi_conversion/tests/__init__.py
ghapi_conversion/tests/test_cli.py
ghapi_conversion/tests/test_setup.py
ghapi_conversion/tests/test_utils.py
ghapi_conversion/tests/test_utils_for_tests.py
ghapi_conversion/tests/utils_for_tests.py
ghapi_conversion-0.0.7.dist-info/LICENSE.md
ghapi_conversion-0.0.7.dist-info/METADATA
ghapi_conversion-0.0.7.dist-info/WHEEL
ghapi_conversion-0.0.7.dist-info/top_level.txt
ghapi_conversion-0.0.7.dist-info/RECORD
